taskgraph/__init__.py
taskgraph/config.py
taskgraph/create.py
taskgraph/decision.py
taskgraph/docker.py
taskgraph/filter_tasks.py
taskgraph/generator.py
taskgraph/graph.py
taskgraph/main.py
taskgraph/morph.py
taskgraph/parameters.py
taskgraph/target_tasks.py
taskgraph/task.py
taskgraph/taskgraph.py
taskgraph/actions/__init__.py
taskgraph/actions/add_new_jobs.py
taskgraph/actions/cancel.py
taskgraph/actions/cancel_all.py
taskgraph/actions/rebuild_cached_tasks.py
taskgraph/actions/registry.py
taskgraph/actions/retrigger.py
taskgraph/actions/util.py
taskgraph/loader/__init__.py
taskgraph/loader/default.py
taskgraph/loader/transform.py
taskgraph/optimize/__init__.py
taskgraph/optimize/base.py
taskgraph/optimize/strategies.py
taskgraph/run-task/fetch-content
taskgraph/run-task/hgrc
taskgraph/run-task/robustcheckout.py
taskgraph/run-task/run-task
taskgraph/transforms/__init__.py
taskgraph/transforms/base.py
taskgraph/transforms/cached_tasks.py
taskgraph/transforms/chunking.py
taskgraph/transforms/code_review.py
taskgraph/transforms/docker_image.py
taskgraph/transforms/fetch.py
taskgraph/transforms/from_deps.py
taskgraph/transforms/matrix.py
taskgraph/transforms/notify.py
taskgraph/transforms/task.py
taskgraph/transforms/task_context.py
taskgraph/transforms/run/__init__.py
taskgraph/transforms/run/common.py
taskgraph/transforms/run/index_search.py
taskgraph/transforms/run/run_task.py
taskgraph/transforms/run/toolchain.py
taskgraph/util/__init__.py
taskgraph/util/archive.py
taskgraph/util/attributes.py
taskgraph/util/cached_tasks.py
taskgraph/util/caches.py
taskgraph/util/copy.py
taskgraph/util/dependencies.py
taskgraph/util/docker.py
taskgraph/util/hash.py
taskgraph/util/json.py
taskgraph/util/keyed_by.py
taskgraph/util/parameterization.py
taskgraph/util/path.py
taskgraph/util/python_path.py
taskgraph/util/readonlydict.py
taskgraph/util/schema.py
taskgraph/util/set_name.py
taskgraph/util/shell.py
taskgraph/util/taskcluster.py
taskgraph/util/taskgraph.py
taskcluster_taskgraph-17.3.0.dist-info/METADATA
taskcluster_taskgraph-17.3.0.dist-info/WHEEL
taskcluster_taskgraph-17.3.0.dist-info/entry_points.txt
taskcluster_taskgraph-17.3.0.dist-info/licenses/LICENSE
taskcluster_taskgraph-17.3.0.dist-info/RECORD
