Metadata-Version: 2.4
Name: taskcluster-taskgraph
Version: 17.3.0
Summary: Build taskcluster taskgraphs
Project-URL: Repository, https://github.com/taskcluster/taskgraph
Project-URL: Issues, https://github.com/taskcluster/taskgraph/issues
Author-email: Mozilla Release Engineering <release+taskgraph@mozilla.com>
License-File: LICENSE
Classifier: Development Status :: 5 - Production/Stable
Classifier: Environment :: Console
Classifier: License :: OSI Approved :: Mozilla Public License 2.0 (MPL 2.0)
Classifier: Programming Language :: Python :: 3.9
Classifier: Programming Language :: Python :: 3.10
Classifier: Programming Language :: Python :: 3.11
Classifier: Programming Language :: Python :: 3.12
Classifier: Programming Language :: Python :: 3.13
Classifier: Programming Language :: Python :: 3.14
Classifier: Topic :: Software Development
Requires-Python: >=3.9
Requires-Dist: appdirs>=1.4
Requires-Dist: cookiecutter~=2.1
Requires-Dist: json-e>=2.7
Requires-Dist: mozilla-repo-urls
Requires-Dist: pyyaml>=5.3.1
Requires-Dist: redo>=2.0
Requires-Dist: requests>=2.25
Requires-Dist: slugid>=2.0
Requires-Dist: taskcluster-urls>=11.0
Requires-Dist: taskcluster<92.0,>=91.0
Requires-Dist: voluptuous>=0.12.1
Provides-Extra: load-image
Requires-Dist: zstandard; extra == 'load-image'
Provides-Extra: orjson
Requires-Dist: orjson; extra == 'orjson'
